pb2/__init__.py
pb2/pb2.cp311-win_amd64.pyd
pb2/pb2.cp312-win_amd64.pyd
pb2/pb2.cp313-win_amd64.pyd
pybooster2-0.4.12.dist-info/licenses/LICENSE
pybooster2-0.4.12.dist-info/METADATA
pybooster2-0.4.12.dist-info/WHEEL
pybooster2-0.4.12.dist-info/top_level.txt
pybooster2-0.4.12.dist-info/RECORD
